{
  "main": {
    "id": "317c27bfcc5a8c2e",
    "type": "split",
    "children": [
      {
        "id": "bc27e06adad6dca9",
        "type": "tabs",
        "children": [
          {
            "id": "f8a5e2ea93e2c3a4",
            "type": "leaf",
            "state": {
              "type": "markdown",
              "state": {
                "file": "Excalidraw/Inferno Board.md",
                "mode": "source",
                "source": false
              },
              "icon": "lucide-file",
              "title": "Inferno Board"
            }
          },
          {
            "id": "9e952d6aaf078f1c",
            "type": "leaf",
            "state": {
              "type": "bases",
              "state": {
                "file": "Bases.base",
                "viewName": "View"
              },
              "icon": "lucide-table",
              "title": "Bases"
            }
          }
        ]
      }
    ],
    "direction": "vertical"
  },
  "left": {
    "id": "3913473e35800052",
    "type": "split",
    "children": [
      {
        "id": "e188e63fc4b3c4e3",
        "type": "tabs",
        "children": [
          {
            "id": "1e52d25cfc7e36e8",
            "type": "leaf",
            "state": {
              "type": "file-explorer",
              "state": {
                "sortOrder": "alphabetical",
                "autoReveal": false
              },
              "icon": "lucide-folder-closed",
              "title": "Files"
            }
          },
          {
            "id": "b533c80ab2b35557",
            "type": "leaf",
            "state": {
              "type": "search",
              "state": {
                "query": "",
                "matchingCase": false,
                "explainSearch": false,
                "collapseAll": false,
                "extraContext": false,
                "sortOrder": "alphabetical"
              },
              "icon": "lucide-search",
              "title": "Search"
            }
          },
          {
            "id": "1858e4f2b1bd043d",
            "type": "leaf",
            "state": {
              "type": "bookmarks",
              "state": {},
              "icon": "lucide-bookmark",
              "title": "Bookmarks"
            }
          }
        ]
      }
    ],
    "direction": "horizontal",
    "width": 300
  },
  "right": {
    "id": "9fed350c2a5d81e7",
    "type": "split",
    "children": [
      {
        "id": "5b86859dd89afa75",
        "type": "tabs",
        "children": [
          {
            "id": "10cadaf26ed6df3c",
            "type": "leaf",
            "state": {
              "type": "backlink",
              "state": {
                "file": "Mirage/Mirage Nades/Cat smoke.md",
                "collapseAll": false,
                "extraContext": false,
                "sortOrder": "alphabetical",
                "showSearch": false,
                "searchQuery": "",
                "backlinkCollapsed": false,
                "unlinkedCollapsed": true
              },
              "icon": "links-coming-in",
              "title": "Backlinks for Cat smoke"
            }
          },
          {
            "id": "bad95e4919170f60",
            "type": "leaf",
            "state": {
              "type": "outgoing-link",
              "state": {
                "file": "Mirage/Mirage Nades/Cat smoke.md",
                "linksCollapsed": false,
                "unlinkedCollapsed": true
              },
              "icon": "links-going-out",
              "title": "Outgoing links from Cat smoke"
            }
          },
          {
            "id": "2d3f520cccea92b6",
            "type": "leaf",
            "state": {
              "type": "tag",
              "state": {
                "sortOrder": "frequency",
                "useHierarchy": true,
                "showSearch": false,
                "searchQuery": ""
              },
              "icon": "lucide-tags",
              "title": "Tags"
            }
          },
          {
            "id": "e40de45ff0c847fd",
            "type": "leaf",
            "state": {
              "type": "outline",
              "state": {
                "file": "Mirage/Mirage Nades/Cat smoke.md",
                "followCursor": false,
                "showSearch": false,
                "searchQuery": ""
              },
              "icon": "lucide-list",
              "title": "Outline of Cat smoke"
            }
          },
          {
            "id": "75996e348b15ba7c",
            "type": "leaf",
            "state": {
              "type": "git-view",
              "state": {},
              "icon": "git-pull-request",
              "title": "Source Control"
            }
          }
        ],
        "currentTab": 4
      }
    ],
    "direction": "horizontal",
    "width": 300
  },
  "left-ribbon": {
    "hiddenItems": {
      "bases:Create new base": false,
      "switcher:Open quick switcher": false,
      "graph:Open graph view": false,
      "canvas:Create new canvas": false,
      "daily-notes:Open today's daily note": false,
      "templates:Insert template": false,
      "command-palette:Open command palette": false,
      "obsidian-excalidraw-plugin:New drawing": false,
      "obsidian-git:Open Git source control": false
    }
  },
  "active": "75996e348b15ba7c",
  "lastOpenFiles": [
    "Train/Train Nades/Train Hell Smoke.md",
    "Overpass/Overpass Nades/Overpass Bank Smoke from Party.md",
    "Overpass/Overpass Nades/Overpass A exec from long.md",
    "Overpass/Overpass Nades/Heaven smoke from midsite B.md",
    "Overpass/Overpass Nades/Heaven Smoke from Monster.md",
    "Overpass/Overpass Nades/Fountain flash for CTs to peek.md",
    "Nuke/Tips & Tricks/Nuke squeaky HE play.md",
    "Nuke/Tips & Tricks/Nuke ramp bait push.md",
    "Nuke/Tips & Tricks",
    "Nuke/Nuke Nades/Nuke Hooxi Inner Smoke.md",
    "Mirage/Tips & Tricks/Blocking mid window smoke play.md",
    "Mirage/Mirage Nades/Top mid molotov lineup for the boxes.md",
    "Mirage/Mirage Nades/Short Molotov Mirage.md",
    "Mirage/Mirage Nades/Mirage Cat Flash.md",
    "Mirage/Mirage Nades/Default A Mirage Molly.md",
    "Inferno/Tips & Tricks/Inferno mid boost.md",
    "Inferno/Tips & Tricks/Inferno Apts Double Peek Eco.md",
    "Inferno/Inferno Nades/Pit Molly Lineup.md",
    "Inferno/Inferno Nades/Inferno Dark Molly Retake.md",
    "Inferno/Inferno Nades/Inferno Coffin Molly.md",
    "Inferno/Inferno Nades/Inferno Arch Smoke from Alt mid.md",
    "Inferno/Inferno Nades/Crazy A Molotovs from Apts.md",
    "Dust 2/Tips & Tricks/Dust2 off angle pit.md",
    "Dust 2/Tips & Tricks",
    "Dust 2/Dust 2 Nades/Dust remoke door.md",
    "Dust 2/Dust 2 Nades/Defensive Long A Smoke.md",
    "Ancient/Ancient Nades/Ancient retake cave flash.md",
    "Ancient/Ancient Nades/Ancient Nade HE.md",
    "Bases.base",
    "Nonmd/target/debug/deps/EasyMDNades-53332016985cf7fc",
    "Nonmd/target/debug/incremental/EasyMDNades-2nucsy25gncni/s-h9ylaurew0-0dmhhee-ctdkr2aonubsqsv42pvkr4r5p/work-products.bin",
    "Nonmd/target/debug/incremental/EasyMDNades-2nucsy25gncni/s-h9ylaurew0-0dmhhee-ctdkr2aonubsqsv42pvkr4r5p/query-cache.bin",
    "Nonmd/target/debug/incremental/EasyMDNades-2nucsy25gncni/s-h9ylaurew0-0dmhhee-ctdkr2aonubsqsv42pvkr4r5p/f2ts2sfzb33s8ihfpqmi9x4fr.o",
    "Nonmd/target/debug/incremental/EasyMDNades-2nucsy25gncni/s-h9ylaurew0-0dmhhee-ctdkr2aonubsqsv42pvkr4r5p/ewm8949il4ujl2odoo229zr0g.o",
    "Nonmd/target/debug/incremental/EasyMDNades-2nucsy25gncni/s-h9ylaurew0-0dmhhee-ctdkr2aonubsqsv42pvkr4r5p/ejhi3gzbxea7mn3evp4qbg3vs.o",
    "Nonmd/target/debug/incremental/EasyMDNades-2nucsy25gncni/s-h9ylaurew0-0dmhhee-ctdkr2aonubsqsv42pvkr4r5p/e1au4z8rixirftymj14qzdnrl.o",
    "Train/images/Train Setup.png"
  ]
}